<QuestDialog xmlns:xsi="http://www.w3.org/2001/XMLSchema-instance" xsi:schemaLocation="https://vezel.dev/novadrop/dc/QuestDialog QuestDialog.xsd" id="49" huntingZoneId="19" voiceTypeId="0" xmlns="https://vezel.dev/novadrop/dc/QuestDialog">
    <Text id="1" huntingZoneId="0" prevId="0" villagerId="0" />
    <Text id="100" huntingZoneId="219" prevId="0" villagerId="1031">
        <Page social="0" />
    </Text>
    <Text id="2" huntingZoneId="219" prevId="0" villagerId="1031">
        <Page social="4">I've added up the facts and subtracted the rumors, and I've come to the conclusion that this all began with Sidurek. After he appeared, the Lokians weren't far behind.&lt;NEXTPAGEBUTTON&gt;"And where can I find him?"&lt;/NEXTPAGEBUTTON&gt;</Page>
        <Page social="4">He'a usually somewhere near the Free Brotherhood stronghold. He may not be alone, so be careful.</Page>
    </Text>
    <Text id="3" huntingZoneId="219" prevId="2" villagerId="1031">
        <Page social="4">A letter? Let's see it. It's to someone named Malachai.&lt;BR&gt;&lt;BR&gt;I'll look into this. Thank you for helping.</Page>
    </Text>
    <Text id="4" huntingZoneId="219" villagerId="1031">
        <Page social="0">The longer Sidurek lives the worse the problem will become.</Page>
    </Text>
</QuestDialog>
