<Area xmlns:xsi="http://www.w3.org/2001/XMLSchema-instance" xsi:schemaLocation="https://vezel.dev/novadrop/dc/Area Area.xsd" id="478" areaName="EX_HWC_B_SD_P" continentId="9078" nameId="9078001" pcMoveCylinder="true" protect="false" ride="true" worldMapGuardId="12" worldMapWorldId="9999" xmlns="https://vezel.dev/novadrop/dc/Area">
    <Section id="1" priority="1" desc="9078001 비비슈의 실험실" nameId="9078001" pcMoveCylinder="true" protect="false" ride="true" addMaxZ="500" campId="0" desTex="false" duel="false" enableItemId="" floor="1" huntingZoneId="-1" pk="false" restBonus="false" subtractMinZ="500" trade="true" vender="false" worldMapSectionId="9078">
        <Fence pos="-15347.7070,-199673.6563,13050.1406" />
        <Fence pos="659.6499,-204791.6250,10684.7148" />
        <Fence pos="16490.4609,-200241.2500,3808.3594" />
        <Fence pos="15311.2559,-168993.9063,5530.3438" />
        <Fence pos="-15224.7246,-168960.8438,4669.6104" />
        <Fence pos="-15233.6738,-173589.6563,3558.6816" />
        <Fence pos="-15279.8867,-182918.5469,6513.0186" />
        <Fence pos="-15108.3301,-189030.1250,11025.5645" />
        <Fence pos="-14958.5771,-192466.2813,10177.5088" />
        <Section id="2" priority="11" desc="9078002 비비슈의 통제 실험실" nameId="9078002" pcMoveCylinder="true" protect="false" ride="true" addMaxZ="500" campId="0" desTex="false" duel="false" enableItemId="" floor="1" huntingZoneId="-1" pk="false" restBonus="false" subtractMinZ="1000" trade="true" vender="false" worldMapSectionId="0">
            <Fence pos="-11601.1006,-195314.8281,9557.5625" />
            <Fence pos="-10758.7871,-193462.2344,8715.5488" />
            <Fence pos="-10665.2041,-191957.9063,8545.3594" />
            <Fence pos="-10861.7959,-191505.2813,8543.7402" />
            <Fence pos="-12001.3232,-190671.0781,8539.7402" />
            <Fence pos="-12163.2949,-190319.9063,8622.4453" />
            <Fence pos="-14652.7969,-188857.9063,11587.5840" />
            <Fence pos="-14915.6396,-194460.9531,11129.5420" />
        </Section>
        <Section id="3" priority="12" desc="9078003 저주받은 카이둔군 본영" nameId="9078003" pcMoveCylinder="true" protect="false" ride="true" addMaxZ="500" campId="0" desTex="false" duel="false" enableItemId="" floor="1" huntingZoneId="-1" pk="false" restBonus="false" subtractMinZ="1000" trade="true" vender="false" worldMapSectionId="0">
            <Fence pos="-8450.7598,-182759.9531,6590.4639" />
            <Fence pos="-8439.5938,-184370.3594,6974.3516" />
            <Fence pos="-7408.7510,-186984.8125,7511.6094" />
            <Fence pos="-7485.8457,-187569.6250,8654.6875" />
            <Fence pos="-5804.8652,-188145.7813,8505.4199" />
            <Fence pos="-5093.2900,-187931.9219,8323.9180" />
            <Fence pos="-4057.4634,-187268.4688,8428.0205" />
            <Fence pos="-4347.6265,-185577.8281,7889.7896" />
            <Fence pos="-2756.1260,-184828.8281,7413.0479" />
            <Fence pos="-1177.3877,-184519.2031,8008.4170" />
            <Fence pos="408.1226,-183790.0000,8423.5879" />
            <Fence pos="1436.9147,-182586.1406,8327.6543" />
            <Fence pos="907.6110,-180326.0781,8016.4751" />
            <Fence pos="159.8049,-179744.6250,6562.0781" />
            <Fence pos="-619.4692,-178284.5000,6552.1187" />
            <Fence pos="-2258.1255,-176982.9219,6465.8149" />
            <Fence pos="-3698.1084,-177549.2969,7015.3584" />
            <Fence pos="-5551.5513,-177856.7188,6987.3989" />
            <Fence pos="-6869.5303,-175836.0156,6090.3193" />
            <Fence pos="-8646.0527,-176679.4063,6098.5215" />
            <Fence pos="-10657.4561,-178034.8750,5937.9912" />
            <Fence pos="-11154.0840,-179238.6094,5965.7036" />
            <Fence pos="-11022.4873,-180413.5156,6053.7275" />
            <Fence pos="-9924.9971,-182087.7188,6252.1167" />
        </Section>
        <Section id="4" priority="13" desc="9078004 저주받은 본영 조사 캠프" nameId="9078004" pcMoveCylinder="true" protect="false" ride="true" addMaxZ="500" campId="0" desTex="false" duel="false" enableItemId="" floor="1" huntingZoneId="-1" pk="false" restBonus="false" subtractMinZ="1000" trade="true" vender="false" worldMapSectionId="0">
            <Fence pos="-12008.8311,-180819.9063,6026.8301" />
            <Fence pos="-12079.5957,-179493.2344,6061.4326" />
            <Fence pos="-13353.4980,-179468.7031,6494.2305" />
            <Fence pos="-13582.6201,-180761.4219,6384.8115" />
            <Fence pos="-13138.3975,-181347.3281,6240.7002" />
        </Section>
    </Section>
</Area>
