<QuestDialog xmlns:xsi="http://www.w3.org/2001/XMLSchema-instance" xsi:schemaLocation="https://vezel.dev/novadrop/dc/QuestDialog QuestDialog.xsd" id="21" huntingZoneId="16" voiceTypeId="0" xmlns="https://vezel.dev/novadrop/dc/QuestDialog">
    <Text id="1" huntingZoneId="0" prevId="0" villagerId="0" />
    <Text id="100" huntingZoneId="67" prevId="0" villagerId="1007">
        <Page social="0" />
    </Text>
    <Text id="2" huntingZoneId="67" prevId="0" villagerId="1007">
        <Page social="5">Мне нужно передать посылку через моего гонца, Джадана, но я нигде не могу его найти.&lt;BR&gt;&lt;BR&gt;&lt;PCNAME&gt;, спроси {@LinkCreature:67#1008#Окона} у северных ворот, не видел ли он, как Джадан уходил?</Page>
    </Text>
    <Text id="3" huntingZoneId="67" prevId="2" villagerId="1008">
        <Page social="5">Джадан? Нет, сегодня я его не видел.&lt;BR&gt;&lt;BR&gt;На всякий случай спроси еще {@LinkCreature:67#1019#Крипу}.</Page>
    </Text>
    <Text id="4" huntingZoneId="67" prevId="3" villagerId="1019">
        <Page social="5">Как-как его зовут?.. Джадан? Да, конечно. Он со своим мальчиком прошел тут некоторое время назад. Он отправился в &lt;font color='#660000'&gt;Долину Клыка&lt;/font&gt;. Сказал, что будет собирать там травы.&lt;BR&gt;&lt;BR&gt;Теперь, подумав, я понимаю, что он здорово задерживается.</Page>
    </Text>
    <Text id="5" huntingZoneId="216" prevId="4" villagerId="1013">
        <Page social="5">(Рядом с собранными травами лежит тело попори. Из-за густой шерсти его не так легко осмотреть, но тут вы постепенно понимаете, что в его венах совсем не осталось крови.)</Page>
    </Text>
    <Text id="6" huntingZoneId="67" prevId="5" villagerId="1019">
        <Page social="5">Что с ним? Ох... как-то это неправильно. Как же такое могло случиться?&lt;BR&gt;&lt;BR&gt;Об этом стоит немедленно сообщить Пака.</Page>
    </Text>
    <Text id="7" huntingZoneId="67" prevId="6" villagerId="1007">
        <Page social="5">Джадан мертв? Какой ужас. В последнее время творятся странные вещи. Лучше нам всем теперь работать в паре.&lt;BR&gt;&lt;BR&gt;Постой, а где же его сын, Дипа?</Page>
    </Text>
</QuestDialog>
