<QuestDialog xmlns:xsi="http://www.w3.org/2001/XMLSchema-instance" xsi:schemaLocation="https://vezel.dev/novadrop/dc/QuestDialog QuestDialog.xsd" id="1" huntingZoneId="122" voiceTypeId="0" xmlns="https://vezel.dev/novadrop/dc/QuestDialog">
    <Text id="1" huntingZoneId="0" prevId="0" villagerId="0" />
    <Text id="100" huntingZoneId="122" prevId="0" villagerId="220021">
        <Page social="0" />
    </Text>
    <Text id="2" huntingZoneId="122" prevId="0" villagerId="220021">
        <Page social="1">Друг, Союзу Просвещенных нужна помощь, если мы хотим преуспеть в добыче ноктиния.&lt;BR&gt;&lt;BR&gt;Мы установили экстракторы ноктиния здесь, на нашей земле, но вокруг постоянно крутятся огромные животные - в основном василиски. Разрушения, которые они вызывают, мешают нам собирать ноктиний. Пожалуйста, помешай этим тварям разрушать наши экстракторы!&lt;BR&gt;&lt;BR&gt;&lt;font color='#660000'&gt;Если члены Союза 65 уровня помогут в этом задании членам Союза Просвещенных меньше уровнем, они получат дополнительную награду.&lt;/font&gt;</Page>
    </Text>
    <Text id="3" huntingZoneId="122" prevId="2" villagerId="220021">
        <Page social="0">Спасибо, друг &lt;PCNAME&gt;!&lt;BR&gt;С твоей помощью союз победит.&lt;BR&gt;Славься Союз Просвещенных!</Page>
    </Text>
</QuestDialog>
