<QuestDialog xmlns:xsi="http://www.w3.org/2001/XMLSchema-instance" xsi:schemaLocation="https://vezel.dev/novadrop/dc/QuestDialog QuestDialog.xsd" id="21" huntingZoneId="22" voiceTypeId="0" xmlns="https://vezel.dev/novadrop/dc/QuestDialog">
    <Text id="1" huntingZoneId="0" prevId="0" villagerId="0" />
    <Text id="100" huntingZoneId="223" prevId="0" villagerId="1010">
        <Page social="0" />
    </Text>
    <Text id="2" huntingZoneId="223" prevId="0" villagerId="1010">
        <Page social="5">{@LinkCreature:223#1054#Дулулу} разведал ситуацию в Окрестностях Жуткой академии. Похоже, что это место просто кишит опасными тварями. Если собираешь туда, то спроси его, на что нужно обращать внимание.</Page>
    </Text>
    <Text id="3" huntingZoneId="223" prevId="2" villagerId="1054">
        <Page social="5">Я скажу тебе, на что нужно обратить внимание: в первую голову на отсутствие у тебя чувства самосохранения. Потому что только безумец полезет в это богом забытое место.&lt;BR&gt;&lt;BR&gt;Но если все же отправишься туда, попытайся уничтожить как можно больше {@LinkCreature:22#4#Вадомских кентавров}, {@LinkCreature:22#5#Мастеровых гномов} и {@LinkCreature:22#3#Гномов-жезлоносцев}.&lt;BR&gt;&lt;BR&gt;Нужно расчистить путь к дворцу, если ты хочешь, чтобы мы смогли хоть как-то помочь.&lt;NEXTPAGEBUTTON&gt;"Я не оставлю вас в беде".&lt;/NEXTPAGEBUTTON&gt;</Page>
        <Page social="5">Спасибо, &lt;PCNAME&gt;. Ты молодец, знаешь об этом?</Page>
    </Text>
    <Text id="4" huntingZoneId="222" prevId="3" villagerId="1005">
        <Page social="5">Слава Богу, тебе удалось разобраться с кентаврами и гномами. Здесь слишком много опасностей, поэтому не стоит терять времени. Надеюсь, что за тобой придут и другие.&lt;BR&gt;&lt;BR&gt;У нас появится шанс спастись с такими бравыми солдатами, как ты.</Page>
    </Text>
</QuestDialog>
