<QuestDialog xmlns:xsi="http://www.w3.org/2001/XMLSchema-instance" xsi:schemaLocation="https://vezel.dev/novadrop/dc/QuestDialog QuestDialog.xsd" id="25" huntingZoneId="38" voiceTypeId="0" xmlns="https://vezel.dev/novadrop/dc/QuestDialog">
    <Text id="1" huntingZoneId="0" prevId="0" villagerId="0" />
    <Text id="100" huntingZoneId="238" prevId="0" villagerId="1017">
        <Page social="0" />
    </Text>
    <Text id="2" huntingZoneId="238" prevId="0" villagerId="1017">
        <Page social="5">На Заставе у кратера понадобилась древесина для укрепления частокола. Из Эленеи древесина не поступает, а Фанис говорит, что мы не можем рубить здесь деревья. "Особенная экология" и все такое.&lt;BR&gt;&lt;BR&gt;Так что вот мой план. Тебе уже доводилось натыкаться на огромных арбосков на юго-западе, не так ли? Я сам не могу с ними справиться, ну вдруг &lt;PCNAME&gt; сможет нас выручить? Пусть лучше дерево постоит в частоколе, а не будет шляться туда-сюда.&lt;BR&gt;&lt;BR&gt;Да, и не забывай про бесов!</Page>
    </Text>
    <Text id="3" huntingZoneId="238" prevId="2" villagerId="1008">
        <Page social="5">С новым частоколом мы сможем защититься, если нападет Киллиан. Не то что раньше...</Page>
    </Text>
    <Text id="4" huntingZoneId="238" villagerId="1008">
        <Page social="0">Нам нужно больше древесины, чтобы укрепить частокол.</Page>
    </Text>
</QuestDialog>
