<StrSheet_Dungeon xmlns:xsi="http://www.w3.org/2001/XMLSchema-instance" xsi:schemaLocation="https://vezel.dev/novadrop/dc/StrSheet_Dungeon StrSheet_Dungeon.xsd" xmlns="https://vezel.dev/novadrop/dc/StrSheet_Dungeon">
    <String id="9885001" string="Euer Sieg macht mich nur stärker. Bereitet Euch auf die nächste Herausforderung vor!" />
    <String id="9885002" string="Ist das alles, was Ihr könnt?" />
    <String id="9885003" string="Hey, das ist leicht genug für Euch." />
    <String id="9885004" string="So viel zu den Meistern des Traumes." />
    <String id="9885005" string="Bestimmt Euer Schicksal." />
    <String id="9885006" string="Hmm, vielleicht." />
    <String id="9885007" string="Rechtzeitig, um meine Klauen zu säubern." />
    <String id="9885008" string="Hier werdet Ihr sterben." />
    <String id="9885009" string="Im Inneren befinden sich ein paar Schmuckstücke aus meinem Vorrat, die Euch weiterhelfen." />
    <String id="9885010" string="Beeindruckend!" />
    <String id="9885011" string="Tötet so viele Geister, wie Ihr könnt, wenn Ihr sammeln wollt." />
    <String id="9885012" string="Und außerdem belustigen mich Eure ungeschickten Versuche. Hier ist eine Kostprobe meiner Fähigkeiten." />
    <String id="9885013" string="&lt;font size='30'&gt;Unsichtbare Parasiten strömen auf Euch zu.&lt;/font&gt;" />
    <String id="9885014" string="Bumm, bumm, BUMM!" />
    <String id="9885015" string="Eine Urne ist nur gut, wenn sie zertrümmert wurde." />
    <String id="9885016" string="Wumm! Ich sterbe." />
    <String id="9885017" string="10 vernichtet!" />
    <String id="9885018" string="30 vernichtet!" />
    <String id="9885020" string="50 vernichtet!" />
    <String id="9885021" string="10 Tote!" />
    <String id="9885022" string="30 Tote!" />
    <String id="9885023" string="50 Tote!" />
    <String id="9885024" string="&lt;font size='40'&gt;Ein pulsierender Kristall erscheint.&lt;/font&gt;" />
    <String id="9885026" string="Es wird dunkel." />
    <String id="9885027" string="Der Spiegel gibt ein schimmerndes Licht von sich." />
    <String id="9885028" string="&lt;font size='50'&gt;Tötet die blauen Argonen. Ermächtigte Argonen verringern die Gesundheit des Feindes.&lt;/font&gt;" />
    <String id="9885029" string="&lt;font size='50'&gt;Tötet die roten Argonen. Ermächtigte Argonen erhöhen die Gesundheit des Feindes.&lt;/font&gt;" />
    <String id="9885030" string="Ein Dimensionsspiegel erscheint." />
    <String id="9885031" string="Gute Arbeit. Hier, nehmt diese Belohnung!" />
    <String id="9885032" string="Reinigung!" />
    <String id="9885033" string="Das ist ein Vorgeschmack auf Eure Machtlosigkeit." />
    <String id="9885034" string="Erbärmlich!" />
    <String id="9885036" string="Ich freue mich auf Euren langsamen und schmerzhaften Tod." />
    <String id="9885037" string="Meine Güte! Seid Ihr noch immer hier?" />
    <String id="9885038" string="Hier, nehmt das für Eure Bemühungen." />
    <String id="9885039" string="Passt auf, wo Ihr hintretet. Der Tod lauert überall." />
    <String id="9885043" string="Jetzt angreifen!" />
    <String id="9885046" string="Verstärkung kommt!" />
    <String id="9885047" string="Ihr bleibt siegreich. Beeindruckend." />
    <String id="9885048" string="Hier, Ihr habt diese Belohnung verdient!" />
    <String id="9885049" string="Und noch eine Kostprobe meiner Macht!" />
    <String id="9885050" string="Fahrt unbedingt fort. Euer Handeln amüsiert mich." />
    <String id="9885051" string="Ein dunkles Gespenst nähert sich." />
    <String id="9885052" string="Gebt Ihr nun endlich auf? Erbärmlich." />
    <String id="9885053" string="Das Interessante an Albträumen ist, dass sie nicht vernichtet werden können." />
    <String id="9885101" string="Spitze der Furcht: 1. Herausforderung" />
    <String id="9885102" string="Spitze der Furcht: 2. Herausforderung" />
    <String id="9885103" string="Spitze der Furcht: 3. Herausforderung" />
    <String id="9885104" string="Spitze der Furcht: 4. Herausforderung" />
    <String id="9885105" string="Spitze der Furcht: 5. Herausforderung" />
    <String id="9885106" string="Spitze der Furcht: 6. Herausforderung" />
    <String id="9885107" string="Spitze der Furcht: 7. Herausforderung" />
    <String id="9885108" string="Spitze der Furcht: 8. Herausforderung" />
    <String id="9885109" string="Spitze der Furcht: 9. Herausforderung" />
    <String id="9885110" string="Spitze der Furcht: 10. Herausforderung" />
    <String id="9885111" string="Spitze der Furcht: 11. Herausforderung" />
    <String id="9885112" string="Spitze der Furcht: 12. Herausforderung" />
    <String id="9885113" string="Spitze der Furcht: 13. Herausforderung" />
    <String id="9885114" string="Spitze der Furcht: 14. Herausforderung" />
    <String id="9885115" string="Spitze der Furcht: 15. Herausforderung" />
    <String id="9885116" string="Spitze der Furcht: 16. Herausforderung" />
    <String id="9885117" string="Spitze der Furcht: 17. Herausforderung" />
    <String id="9885118" string="Spitze der Furcht: 18. Herausforderung" />
    <String id="9885119" string="Spitze der Furcht: 19. Herausforderung" />
    <String id="9885120" string="Spitze der Furcht: 20. Herausforderung" />
    <String id="9885199" string="Nun, das war unerwartet. Also gut, Ihr dürft passieren." />
    <String id="9885200" string="Willkommen auf meinem Spielplatz!" />
    <String id="9885201" string="Dieser Turm offenbart Eure finstersten Ängste." />
    <String id="9885202" string="Ich freue mich schon darauf zu sehen wie Eure Albträume wahr werden." />
    <String id="9885203" string="Hier! Zur Einstimmung." />
    <String id="9885204" string="Ihr seid noch am Leben? Immer noch? Beeindruckend." />
    <String id="9885205" string="Hier. Eine kleine Belohnung für Eure bisherigen Mühen." />
    <String id="9885206" string="Ich hoffe, sie gefällt Euch." />
    <String id="9885207" string="Das ist sehr unterhaltsam für mich." />
    <String id="9885208" string="Das sind nur Eure verzweifelten Versuche, zu überleben." />
    <String id="9885209" string="Bitte bleibt noch ein bisschen länger am Leben." />
    <String id="9885210" string="Können wir jetzt so richtig loslegen?" />
    <String id="9885211" string="Gut. Ich wusste, dass Ihr noch mehr Kampfgeist besitzt." />
    <String id="9885212" string="Dann lasst uns jetzt ernsthaft beginnen." />
    <String id="9885213" string="Wirklich beeindruckend! Jedoch ..." />
    <String id="9885214" string="Es ist nur gerecht, wenn ich Euch sage, dass ich mich bisher zurückgehalten habe." />
    <String id="9885215" string="Zuletzt werdet Ihr darum betteln, dass ich Euch schnell töte." />
    <String id="9885216" string="Ehrlich gesagt dachte ich nicht, dass Ihr so weit kommt." />
    <String id="9885217" string="Ich nehme an, dass ich wohl das schlimmste, was Ihr je gesehen habt, veranlassen muss." />
    <String id="9885218" string="Seid Ihr bereit für ein emotionales Wiedersehen mit ..." />
    <String id="9885219" string="Oh ja! War das nicht lustig? Und das war nur der Anfang." />
    <String id="9885220" string="Bedenkt immer ..." />
    <String id="9885221" string="Solange der Traum andauert, sind die Albträume nicht weit weg." />
    <String id="9885222" string="Jemand möchte Euch etwas sagen." />
    <String id="9885223" string="Es ist eher ein Schreien, aber Ihr werdet es schon verstehen." />
    <String id="9885224" string="Habt eine schöne Zeit zusammen." />
    <String id="9885225" string="Den schlimmsten Schmerz empfindet Ihr ..." />
    <String id="9885226" string="Wenn die Wunden zu heilen beginnen." />
    <String id="9885227" string="Möchtet Ihr Euer Glück noch einmal auf die Probe stellen?" />
    <String id="9885228" string="Die meisten, die diesem Gegner begegnen ..." />
    <String id="9885229" string="Ihr seid wohl etwas sprunghaft ..." />
    <String id="9885230" string="Aber Ihr wisst das sicher schon, oder?" />
    <String id="9885231" string="Beeindruckend ... wirklich beeindruckend ..." />
    <String id="9885232" string="Nur ein wahrer Gläubiger hält so lange an seiner Hoffnung fest ..." />
    <String id="9885233" string="Ich schätze, Ihr seid bereit für meine größte Tat." />
    <String id="9885234" string="Beeilt Euch." />
    <String id="9885235" string="Eure eigenen verzerrten Erinnerungen werden Euch vernichten!" />
    <String id="9885236" string="Blindlings anzugreifen wäre dumm, oder?" />
    <String id="9885237" string="Ungeschickte Aufseher fangen an aufzupassen." />
    <String id="9885238" string="Volsurus beginnt aufzupassen." />
    <String id="9885239" string="Werdet nicht übermütig!" />
    <String id="9885240" string="Nun prüfen wir Eure Wahrnehmung." />
    <String id="9885241" string="Öffnet die Augen!" />
    <String id="9885242" string="Mir gefällt es nicht ..." />
    <String id="9885243" string="Ich kann es nicht mehr ertragen, dabei zuzusehen, wie Ihr herumrennt ..." />
    <String id="9885244" string="Ich will, dass Ihr in panischer Angst flieht!" />
    <String id="9885245" string="&lt;font size='50'&gt;Oh, ich lache so gerne!&lt;/font&gt;" />
</StrSheet_Dungeon>
