<StrSheet_Dungeon xmlns:xsi="http://www.w3.org/2001/XMLSchema-instance" xsi:schemaLocation="https://vezel.dev/novadrop/dc/StrSheet_Dungeon StrSheet_Dungeon.xsd" xmlns="https://vezel.dev/novadrop/dc/StrSheet_Dungeon">
    <String id="9077001" string="Sphären der Wüste, greift an!" />
    <String id="9077002" string="Im Lager voraus glitzert etwas rot im Licht." />
    <String id="9077003" string="Im Zentrum der Arena geschieht etwas!" />
    <String id="9077004" string="Die Blutscherbe verlangt nach mehr Blut." />
    <String id="9077005" string="Ein Gladiator betritt die Arena!" />
    <String id="9077006" string="Das war noch nicht das Ende." />
    <String id="9077007" string="Die Blutscherbe ist blutleer." />
    <String id="9077008" string="Ihr spürt unnatürliche Wut in der Umgebung. Vernichtet ihren Ursprung." />
    <String id="9077009" string="Die Magie ist gebrochen." />
    <String id="9077999" string="" />
    <String id="9077010" string="Es ist noch nicht zu Ende!" />
    <String id="9077011" string="Ihr befindet Euch in einem Sandsturmgebiet." />
    <String id="9077012" string="Die Wut verebbt." />
</StrSheet_Dungeon>
