<StrSheet_Quest xmlns:xsi="http://www.w3.org/2001/XMLSchema-instance" xsi:schemaLocation="https://vezel.dev/novadrop/dc/StrSheet_Quest StrSheet_Quest.xsd" xmlns="https://vezel.dev/novadrop/dc/StrSheet_Quest">
    <String id="18208001" string="Nicht vom Arzt empfohlen" />
    <String id="18208002" string="&quot;Ich bin sicher, dass er in der Nähe ist.&quot;" />
    <String id="18208003" string="Sprecht mit Dougal." />
    <String id="18208004" string="&quot;Es würde ihr guttun, sich etwas zu entspannen ...&quot;" />
    <String id="18208005" string="&quot;Okay, aber das ist das letzte Mal.&quot;" />
    <String id="18208006" string="&quot;Vielleicht solltet Ihr sie einfach in Ruhe lassen.&quot;" />
    <String id="18208007" string="Findet Paesen und sprecht mit ihm." />
    <String id="18208008" string="&quot;Gut ... Ich tue, was ich kann.&quot;" />
    <String id="18208009" string="Fleisch der Kreaturen von den heißen Quellen" />
    <String id="18208010" string="Tötet Seesterne der heißen Quellen und Kamara der heißen Quellen, um ihr Fleisch zu erhalten." />
    <String id="18208011" string="Bringt das Fleisch der Kreaturen von den heißen Quellen zu Paesen." />
    <String id="18208012" string="&quot;Ich hoffe, es funktioniert ... in Eurem eigenen Interesse.&quot;" />
    <String id="18208013" string="&quot;Seufz ... In Ordnung. Bringen wir es hinter uns.&quot;" />
    <String id="18208014" string="Fragt Paesen, ob er bereit zur Rückkehr ist." />
    <String id="18208015" string="&quot;Ähm ... Ich muss Renish Bericht erstatten ...&quot;" />
    <String id="18208016" string="Bringt das Stärkungsmittel zu Solyn." />
    <String id="18208017" string="&quot;Verstanden.&quot;" />
    <String id="18208018" string="Bringt den wiederhergestellten Anhänger zu Renish im Amadjuakhandelsposten." />
    <String id="18208019" string="" />
</StrSheet_Quest>
