<StrSheet_Quest xmlns:xsi="http://www.w3.org/2001/XMLSchema-instance" xsi:schemaLocation="https://vezel.dev/novadrop/dc/StrSheet_Quest StrSheet_Quest.xsd" xmlns="https://vezel.dev/novadrop/dc/StrSheet_Quest">
    <String id="4733001" string="Das Späherlager auskundschaften" />
    <String id="4733002" string="Dort könnte sich etwas Nützliches befinden." />
    <String id="4733003" string="Möglicherweise haben wir hier etwas Wichtiges aufgedeckt." />
    <String id="4733004" string="Altes Späherlager" />
    <String id="4733005" string="Ihr habt ein {@Rgn:47013$$Altes Späherlager} gefunden." />
    <String id="4733006" string="Findet das Alte Späherlager, an der Straße nördlich des Vorläufigen Patrouillenlagers." />
    <String id="4733007" string="Öffnet die {@WorkObject:111$$Zerstörte Vorratskiste} und nehmt den Inhalt an Euch." />
    <String id="4733008" string="Tötet {@creature:47#6002$$Poskula}." />
    <String id="4733009" string="{@WorkObject:111$$Zerstörte Vorratskiste}" />
    <String id="4733010" string="Alte Vorräte" />
    <String id="4733011" string="Meldet das Ergebnis {@creature:247#1021$$Shannow} im Vorläufigen Patrouillenlager." />
    <String id="4733012" string="&quot;Ich habe meine Pflicht erfüllt.&quot;" />
</StrSheet_Quest>
