<QuestDialog xmlns:xsi="http://www.w3.org/2001/XMLSchema-instance" xsi:schemaLocation="https://vezel.dev/novadrop/dc/QuestDialog QuestDialog.xsd" id="23" huntingZoneId="9" voiceTypeId="0" xmlns="https://vezel.dev/novadrop/dc/QuestDialog">
    <Text id="1" huntingZoneId="0" prevId="0" villagerId="0" />
    <Text id="100" huntingZoneId="209" prevId="0" villagerId="1005">
        <Page social="0" />
    </Text>
    <Text id="2" huntingZoneId="209" prevId="0" villagerId="1005">
        <Page social="4">Je sais que les soldats comme vous ont des choses plus importantes à faire, mais la situation est devenue tellement tendue que je dois solliciter votre aide.&lt;BR&gt;&lt;BR&gt;Les plaies infligées par les gulas s'infectent pour ainsi dire instantanément. J'ai besoin de fabriquer des bandages imprégnés d'onguent pour traiter ces plaies avant qu'elles ne se mettent à suppurer. J'ai besoin de &lt;FONT COLOR='#660000'&gt;fibres de Shetla&lt;/FONT&gt;.&lt;BR&gt;&lt;BR&gt;Vous en trouverez un peu partout dans le labyrinthe, mais vous pouvez aussi en acheter à d'autres personnes.</Page>
    </Text>
    <Text id="3" huntingZoneId="209" prevId="2" villagerId="1005">
        <Page social="0">Je me doute que la cueillette de plantes n'était pas votre vocation quand vous avez rejoint l'armée, mais nombre de vos frères d'armes vous devront bientôt la vie, &lt;PCNAME&gt;. Merci!&amp;nbsp;</Page>
    </Text>
    <Text id="4" huntingZoneId="209" villagerId="1005">
        <Page social="0">Pour faire court, j'ai encore besoin de &lt;font color='#660000'&gt;fibres de Shetla&lt;/font&gt;, &lt;PCNAME&gt;.</Page>
    </Text>
</QuestDialog>
