<QuestDialog xmlns:xsi="http://www.w3.org/2001/XMLSchema-instance" xsi:schemaLocation="https://vezel.dev/novadrop/dc/QuestDialog QuestDialog.xsd" id="10" huntingZoneId="122" voiceTypeId="0" xmlns="https://vezel.dev/novadrop/dc/QuestDialog">
    <Text id="1" huntingZoneId="0" prevId="0" villagerId="0" />
    <Text id="100" huntingZoneId="122" prevId="0" villagerId="9001">
        <Page social="0" />
    </Text>
    <Text id="2" huntingZoneId="122" prevId="0" villagerId="9001">
        <Page social="1">Mon ami, l'Union des Éclairés a besoin de vous.&lt;BR&gt;&lt;BR&gt;Nos espions présents sur les terres contrôlées par l'Ordre de Fer nous ont fait par de rumeurs troublantes, qui laissent à penser qu'ils envisagent d'utiliser des monstres locaux comme troupes de choc contre nous.&lt;BR&gt;&lt;BR&gt;Ceci demande une enquête plus poussée. S'il vous plaît, rendez-vous sur le territoire de l'Ordre et tuez quelques {@linkcreature:123#202#mugatos obscurs} et  {@linkcreature:123#205#ghilliedhus de la rivière}, puis revenez avec vos trouvailles.</Page>
    </Text>
    <Text id="3" huntingZoneId="122" prevId="2" villagerId="9001">
        <Page social="0">Très bonne performance, cher ami. L'Union des Éclairés a une dette envers vous!&amp;nbsp;</Page>
    </Text>
</QuestDialog>
