<StrSheet_Quest xmlns:xsi="http://www.w3.org/2001/XMLSchema-instance" xsi:schemaLocation="https://vezel.dev/novadrop/dc/StrSheet_Quest StrSheet_Quest.xsd" xmlns="https://vezel.dev/novadrop/dc/StrSheet_Quest">
    <String id="17214001" string="La petite évasion" />
    <String id="17214002" string="&quot;Très bien.&quot;" />
    <String id="17214003" string="Passage vers la Vallée printanière" />
    <String id="17214004" string="Vous voyez un voyageur avec une monture blessée." />
    <String id="17214005" string="Trouvez la route qui mène à la Vallée printanière." />
    <String id="17214006" string="&quot;Allons vous trouver de l'aide.&quot;" />
    <String id="17214007" string="Parlez à Mihog." />
    <String id="17214008" string="&quot; Je l'arrêterai.&quot;" />
    <String id="17214009" string="Parlez à Rhodos." />
    <String id="17214010" string="&quot;Il a pansé ses blessures.&quot;" />
    <String id="17214011" string="Cherchez Mihog." />
    <String id="17214012" string="&quot;Vers l'Ouest ? Merci.&quot;" />
    <String id="17214013" string="Vérifiez si les gobelins ont repéré Mihog." />
    <String id="17214014" string="&quot;Juste un peu.&quot;" />
    <String id="17214015" string="Parlez à la sentinelle." />
    <String id="17214016" string="&quot;Je me demande...&quot;" />
    <String id="17214017" string="Trouvez Mihog." />
</StrSheet_Quest>
