<QuestDialog xmlns:xsi="http://www.w3.org/2001/XMLSchema-instance" xsi:schemaLocation="https://vezel.dev/novadrop/dc/QuestDialog QuestDialog.xsd" id="93" huntingZoneId="39" voiceTypeId="0" xmlns="https://vezel.dev/novadrop/dc/QuestDialog">
    <Text id="1" huntingZoneId="0" prevId="0" villagerId="0" />
    <Text id="100" huntingZoneId="75" prevId="0" villagerId="1024">
        <Page social="0" />
    </Text>
    <Text id="2" huntingZoneId="75" prevId="0" villagerId="1024">
        <Page social="0">Wird Zeit, den großen bösen Jungs zu zeigen, wo der Hammer hängt! Schaltet die {@LinkCreature:39#200#Klauenreiteraufseher} um das Lager der Vergeltung herum aus.&lt;BR&gt;&lt;BR&gt;Meldet Euch bei Ordinio im Lager der Vergeltung, wenn die Mission abgeschlossen ist.</Page>
    </Text>
    <Text id="3" huntingZoneId="239" prevId="2" villagerId="1005">
        <Page social="4">Die Föderation dankt Euch für Eure Mühen.</Page>
    </Text>
    <Text id="4" huntingZoneId="239" villagerId="1005">
        <Page social="0">Sucht Ihr Arbeit?</Page>
    </Text>
</QuestDialog>
