<QuestDialog xmlns:xsi="http://www.w3.org/2001/XMLSchema-instance" xsi:schemaLocation="https://vezel.dev/novadrop/dc/QuestDialog QuestDialog.xsd" id="33" huntingZoneId="17" voiceTypeId="0" xmlns="https://vezel.dev/novadrop/dc/QuestDialog">
    <Text id="1" huntingZoneId="0" prevId="0" villagerId="0" />
    <Text id="100" huntingZoneId="217" prevId="0" villagerId="1013">
        <Page social="0" />
    </Text>
    <Text id="2" huntingZoneId="217" prevId="0" villagerId="1013">
        <Page social="5">Ihr da! Ich brauche Eure Hilfe. Der Kult überfällt unsere Karren und stiehlt unsere Lebensmittel. Das passiert immer dann, wenn die Wache gerade am schwächsten ist, und sogar wenn wir eine andere Route nehmen. Gemeiner Trick, was?&lt;BR&gt;&lt;BR&gt;Schmeckt für mich ganz nach Verrat.&lt;BR&gt;&lt;BR&gt;Aufseher {@LinkCreature:17#201#Drescher Rotcarn} führt diese Überfälle an. Er zieht aus irgendeinem Grund Truppen auf dem Feld zusammen. Tötet ihn. Durchsucht seine Leiche nach Hinweisen. Setzen wir dem Ganzen ein Ende! Habt Ihr alles mitbekommen?</Page>
    </Text>
    <Text id="3" huntingZoneId="217" prevId="2" villagerId="1013">
        <Page social="5">Da zieh mir einer bei lebendigem Leibe das Fell über die Ohren! Nur vertrauenswürdige Offiziere erhalten diese Verzeichnisse! Wären sie gestohlen worden, hätte es jemand gemeldet. Das wurde nicht gestohlen, sondern freiwillig hergegeben. Das ist wirklich bitter.</Page>
    </Text>
    <Text id="4" huntingZoneId="217" villagerId="1013">
        <Page social="0">Ist Rotcarn schon tot? Nein? Dann möchte ich nichts weiter hören!</Page>
    </Text>
</QuestDialog>
