<QuestDialog xmlns:xsi="http://www.w3.org/2001/XMLSchema-instance" xsi:schemaLocation="https://vezel.dev/novadrop/dc/QuestDialog QuestDialog.xsd" id="26" huntingZoneId="40" voiceTypeId="0" xmlns="https://vezel.dev/novadrop/dc/QuestDialog">
    <Text id="1" huntingZoneId="0" prevId="0" villagerId="0" />
    <Text id="100" huntingZoneId="240" prevId="0" villagerId="1016">
        <Page social="0" />
    </Text>
    <Text id="2" huntingZoneId="240" prevId="0" villagerId="1016">
        <Page social="4">Seit die {@LinkCreature:40#11#Selvarasspäherinnen} auftauchten, verschwinden Leute. Bisher hat niemand Lösegeld verlangt, aber vielleicht werden sie auch versklavt.&lt;BR&gt;&lt;BR&gt;Einige von ihnen zu töten, lässt sie das vielleicht noch einmal überdenken. Also setze ich ein Kopfgeld für jede identifizierbare Marke aus, die Ihr an ihren Körpern finden könnt.</Page>
    </Text>
    <Text id="3" huntingZoneId="240" prevId="2" villagerId="1016">
        <Page social="4">Habt Ihr keinen der Vermissten gesehen? Niemanden?&lt;BR&gt;&lt;BR&gt;Das bedeutet wohl, dass sie schon sehr weit weg sein müssen.&lt;BR&gt;&lt;BR&gt;Trotzdem, danke für Eure Hilfe.</Page>
    </Text>
    <Text id="4" huntingZoneId="240" villagerId="1016">
        <Page social="0">Die {@LinkCreature:40#11#Selvarasspäherinnen} tragen bestimmt eine Art Identifikationsmarke bei sich. Die brauche ich.</Page>
    </Text>
</QuestDialog>
